{
    "type": "FeatureCollection",
    "features": [
        {
            "type": "Feature",
            "properties": {
                "dead": "0",
                "hurt": "1"
            },
            "geometry": {
                "type": "Point",
                "coordinates": [
                    120.653645545511,
                    24.1409812090482
                ]
            }
        },
        {
            "type": "Feature",
            "properties": {
                "dead": "0",
                "hurt": "1"
            },
            "geometry": {
                "type": "Point",
                "coordinates": [
                    120.654570481461,
                    24.1388891174047
                ]
            }
        },
        {
            "type": "Feature",
            "properties": {
                "dead": "0",
                "hurt": "1"
            },
            "geometry": {
                "type": "Point",
                "coordinates": [
                    120.652033742877,
                    24.1388671470193
                ]
            }
        },
        {
            "type": "Feature",
            "properties": {
                "dead": "0",
                "hurt": "1"
            },
            "geometry": {
                "type": "Point",
                "coordinates": [
                    120.653026531215,
                    24.1388866208561
                ]
            }
        },
        {
            "type": "Feature",
            "properties": {
                "dead": "0",
                "hurt": "1"
            },
            "geometry": {
                "type": "Point",
                "coordinates": [
                    120.649936712067,
                    24.1388574853374
                ]
            }
        },
        {
            "type": "Feature",
            "properties": {
                "dead": "0",
                "hurt": "1"
            },
            "geometry": {
                "type": "Point",
                "coordinates": [
                    120.651819468992,
                    24.1360911238792
                ]
            }
        }
    ]
}