{
    "type": "FeatureCollection",
    "features": [
        {
            "type": "Feature",
            "properties": {
                "dead": "0",
                "hurt": "1"
            },
            "geometry": {
                "type": "Point",
                "coordinates": [
                    0,
                    0
                ]
            }
        },
        {
            "type": "Feature",
            "properties": {
                "dead": "0",
                "hurt": "1"
            },
            "geometry": {
                "type": "Point",
                "coordinates": [
                    120.531071668638,
                    24.1679182836975
                ]
            }
        },
        {
            "type": "Feature",
            "properties": {
                "dead": "0",
                "hurt": "2"
            },
            "geometry": {
                "type": "Point",
                "coordinates": [
                    0,
                    0
                ]
            }
        }
    ]
}