{
    "type": "FeatureCollection",
    "features": [
        {
            "type": "Feature",
            "properties": {
                "dead": "0",
                "hurt": "1"
            },
            "geometry": {
                "type": "Point",
                "coordinates": [
                    120.63022426547,
                    24.2100130127366
                ]
            }
        },
        {
            "type": "Feature",
            "properties": {
                "dead": "0",
                "hurt": "1"
            },
            "geometry": {
                "type": "Point",
                "coordinates": [
                    120.63255166537,
                    24.2124448264249
                ]
            }
        },
        {
            "type": "Feature",
            "properties": {
                "dead": "0",
                "hurt": "1"
            },
            "geometry": {
                "type": "Point",
                "coordinates": [
                    120.632557387639,
                    24.2124395665738
                ]
            }
        },
        {
            "type": "Feature",
            "properties": {
                "dead": "0",
                "hurt": "2"
            },
            "geometry": {
                "type": "Point",
                "coordinates": [
                    120.633014420064,
                    24.2127297446052
                ]
            }
        },
        {
            "type": "Feature",
            "properties": {
                "dead": "0",
                "hurt": "2"
            },
            "geometry": {
                "type": "Point",
                "coordinates": [
                    120.644497041689,
                    24.2051873830717
                ]
            }
        },
        {
            "type": "Feature",
            "properties": {
                "dead": "0",
                "hurt": "1"
            },
            "geometry": {
                "type": "Point",
                "coordinates": [
                    120.615505177526,
                    24.218367413078
                ]
            }
        },
        {
            "type": "Feature",
            "properties": {
                "dead": "0",
                "hurt": "1"
            },
            "geometry": {
                "type": "Point",
                "coordinates": [
                    120.633021768283,
                    24.2127172094736
                ]
            }
        },
        {
            "type": "Feature",
            "properties": {
                "dead": "0",
                "hurt": "3"
            },
            "geometry": {
                "type": "Point",
                "coordinates": [
                    120.632558312904,
                    24.212430873891
                ]
            }
        },
        {
            "type": "Feature",
            "properties": {
                "dead": "0",
                "hurt": "1"
            },
            "geometry": {
                "type": "Point",
                "coordinates": [
                    120.632559004606,
                    24.2124439170114
                ]
            }
        },
        {
            "type": "Feature",
            "properties": {
                "dead": "0",
                "hurt": "2"
            },
            "geometry": {
                "type": "Point",
                "coordinates": [
                    120.643515071637,
                    24.2202287974296
                ]
            }
        },
        {
            "type": "Feature",
            "properties": {
                "dead": "0",
                "hurt": "1"
            },
            "geometry": {
                "type": "Point",
                "coordinates": [
                    120.631883323673,
                    24.2052248512685
                ]
            }
        },
        {
            "type": "Feature",
            "properties": {
                "dead": "0",
                "hurt": "1"
            },
            "geometry": {
                "type": "Point",
                "coordinates": [
                    120.600027639359,
                    24.222148482692
                ]
            }
        },
        {
            "type": "Feature",
            "properties": {
                "dead": "0",
                "hurt": "1"
            },
            "geometry": {
                "type": "Point",
                "coordinates": [
                    120.632643342111,
                    24.2385553491623
                ]
            }
        },
        {
            "type": "Feature",
            "properties": {
                "dead": "0",
                "hurt": "2"
            },
            "geometry": {
                "type": "Point",
                "coordinates": [
                    120.631876595292,
                    24.2052249987494
                ]
            }
        },
        {
            "type": "Feature",
            "properties": {
                "dead": "0",
                "hurt": "1"
            },
            "geometry": {
                "type": "Point",
                "coordinates": [
                    0,
                    0
                ]
            }
        },
        {
            "type": "Feature",
            "properties": {
                "dead": "0",
                "hurt": "1"
            },
            "geometry": {
                "type": "Point",
                "coordinates": [
                    0,
                    0
                ]
            }
        },
        {
            "type": "Feature",
            "properties": {
                "dead": "0",
                "hurt": "1"
            },
            "geometry": {
                "type": "Point",
                "coordinates": [
                    120.629649659312,
                    24.2060058242583
                ]
            }
        },
        {
            "type": "Feature",
            "properties": {
                "dead": "0",
                "hurt": "1"
            },
            "geometry": {
                "type": "Point",
                "coordinates": [
                    120.613937581267,
                    24.2359594738446
                ]
            }
        },
        {
            "type": "Feature",
            "properties": {
                "dead": "0",
                "hurt": "2"
            },
            "geometry": {
                "type": "Point",
                "coordinates": [
                    120.615509112147,
                    24.2183638165557
                ]
            }
        },
        {
            "type": "Feature",
            "properties": {
                "dead": "0",
                "hurt": "2"
            },
            "geometry": {
                "type": "Point",
                "coordinates": [
                    120.629592556121,
                    24.2086887949159
                ]
            }
        },
        {
            "type": "Feature",
            "properties": {
                "dead": "0",
                "hurt": "1"
            },
            "geometry": {
                "type": "Point",
                "coordinates": [
                    0,
                    0
                ]
            }
        },
        {
            "type": "Feature",
            "properties": {
                "dead": "0",
                "hurt": "1"
            },
            "geometry": {
                "type": "Point",
                "coordinates": [
                    120.635857080291,
                    24.215497583284
                ]
            }
        },
        {
            "type": "Feature",
            "properties": {
                "dead": "0",
                "hurt": "1"
            },
            "geometry": {
                "type": "Point",
                "coordinates": [
                    120.62905837097,
                    24.2061773756547
                ]
            }
        },
        {
            "type": "Feature",
            "properties": {
                "dead": "0",
                "hurt": "1"
            },
            "geometry": {
                "type": "Point",
                "coordinates": [
                    120.63301677365,
                    24.2127241078926
                ]
            }
        },
        {
            "type": "Feature",
            "properties": {
                "dead": "0",
                "hurt": "1"
            },
            "geometry": {
                "type": "Point",
                "coordinates": [
                    120.63255981309,
                    24.2124377805184
                ]
            }
        },
        {
            "type": "Feature",
            "properties": {
                "dead": "0",
                "hurt": "1"
            },
            "geometry": {
                "type": "Point",
                "coordinates": [
                    120.643180113478,
                    24.2206585946358
                ]
            }
        },
        {
            "type": "Feature",
            "properties": {
                "dead": "0",
                "hurt": "1"
            },
            "geometry": {
                "type": "Point",
                "coordinates": [
                    0,
                    0
                ]
            }
        },
        {
            "type": "Feature",
            "properties": {
                "dead": "0",
                "hurt": "1"
            },
            "geometry": {
                "type": "Point",
                "coordinates": [
                    120.63255981309,
                    24.2124377805184
                ]
            }
        },
        {
            "type": "Feature",
            "properties": {
                "dead": "0",
                "hurt": "3"
            },
            "geometry": {
                "type": "Point",
                "coordinates": [
                    120.646078047993,
                    24.2224802627005
                ]
            }
        },
        {
            "type": "Feature",
            "properties": {
                "dead": "0",
                "hurt": "2"
            },
            "geometry": {
                "type": "Point",
                "coordinates": [
                    120.638498297579,
                    24.2188397752454
                ]
            }
        },
        {
            "type": "Feature",
            "properties": {
                "dead": "0",
                "hurt": "1"
            },
            "geometry": {
                "type": "Point",
                "coordinates": [
                    0,
                    0
                ]
            }
        },
        {
            "type": "Feature",
            "properties": {
                "dead": "0",
                "hurt": "2"
            },
            "geometry": {
                "type": "Point",
                "coordinates": [
                    0,
                    0
                ]
            }
        },
        {
            "type": "Feature",
            "properties": {
                "dead": "0",
                "hurt": "1"
            },
            "geometry": {
                "type": "Point",
                "coordinates": [
                    120.63482085538,
                    24.2118616400281
                ]
            }
        },
        {
            "type": "Feature",
            "properties": {
                "dead": "0",
                "hurt": "1"
            },
            "geometry": {
                "type": "Point",
                "coordinates": [
                    120.613422340131,
                    24.2277750381982
                ]
            }
        },
        {
            "type": "Feature",
            "properties": {
                "dead": "0",
                "hurt": "2"
            },
            "geometry": {
                "type": "Point",
                "coordinates": [
                    0,
                    0
                ]
            }
        },
        {
            "type": "Feature",
            "properties": {
                "dead": "0",
                "hurt": "1"
            },
            "geometry": {
                "type": "Point",
                "coordinates": [
                    120.682770296739,
                    24.1381887021841
                ]
            }
        },
        {
            "type": "Feature",
            "properties": {
                "dead": "0",
                "hurt": "1"
            },
            "geometry": {
                "type": "Point",
                "coordinates": [
                    120.680148011142,
                    24.1403113902818
                ]
            }
        },
        {
            "type": "Feature",
            "properties": {
                "dead": "0",
                "hurt": "1"
            },
            "geometry": {
                "type": "Point",
                "coordinates": [
                    120.636087759858,
                    24.2160873046425
                ]
            }
        },
        {
            "type": "Feature",
            "properties": {
                "dead": "0",
                "hurt": "1"
            },
            "geometry": {
                "type": "Point",
                "coordinates": [
                    0,
                    0
                ]
            }
        },
        {
            "type": "Feature",
            "properties": {
                "dead": "0",
                "hurt": "2"
            },
            "geometry": {
                "type": "Point",
                "coordinates": [
                    0,
                    0
                ]
            }
        },
        {
            "type": "Feature",
            "properties": {
                "dead": "0",
                "hurt": "1"
            },
            "geometry": {
                "type": "Point",
                "coordinates": [
                    0,
                    0
                ]
            }
        },
        {
            "type": "Feature",
            "properties": {
                "dead": "0",
                "hurt": "3"
            },
            "geometry": {
                "type": "Point",
                "coordinates": [
                    0,
                    0
                ]
            }
        },
        {
            "type": "Feature",
            "properties": {
                "dead": "0",
                "hurt": "1"
            },
            "geometry": {
                "type": "Point",
                "coordinates": [
                    0,
                    0
                ]
            }
        },
        {
            "type": "Feature",
            "properties": {
                "dead": "0",
                "hurt": "1"
            },
            "geometry": {
                "type": "Point",
                "coordinates": [
                    0,
                    0
                ]
            }
        },
        {
            "type": "Feature",
            "properties": {
                "dead": "0",
                "hurt": "1"
            },
            "geometry": {
                "type": "Point",
                "coordinates": [
                    120.639565835116,
                    24.205659446622
                ]
            }
        },
        {
            "type": "Feature",
            "properties": {
                "dead": "0",
                "hurt": "2"
            },
            "geometry": {
                "type": "Point",
                "coordinates": [
                    120.632392822477,
                    24.205201857859
                ]
            }
        },
        {
            "type": "Feature",
            "properties": {
                "dead": "0",
                "hurt": "1"
            },
            "geometry": {
                "type": "Point",
                "coordinates": [
                    0,
                    0
                ]
            }
        },
        {
            "type": "Feature",
            "properties": {
                "dead": "0",
                "hurt": "1"
            },
            "geometry": {
                "type": "Point",
                "coordinates": [
                    120.633025832241,
                    24.2127247030712
                ]
            }
        },
        {
            "type": "Feature",
            "properties": {
                "dead": "0",
                "hurt": "1"
            },
            "geometry": {
                "type": "Point",
                "coordinates": [
                    0,
                    0
                ]
            }
        },
        {
            "type": "Feature",
            "properties": {
                "dead": "0",
                "hurt": "2"
            },
            "geometry": {
                "type": "Point",
                "coordinates": [
                    0,
                    0
                ]
            }
        },
        {
            "type": "Feature",
            "properties": {
                "dead": "0",
                "hurt": "1"
            },
            "geometry": {
                "type": "Point",
                "coordinates": [
                    0,
                    0
                ]
            }
        },
        {
            "type": "Feature",
            "properties": {
                "dead": "0",
                "hurt": "2"
            },
            "geometry": {
                "type": "Point",
                "coordinates": [
                    120.639510370724,
                    24.2186921594202
                ]
            }
        }
    ]
}